tariff_td/__init__.py
tariff_td/const.py
tariff_td/tariff_td.py
tariff_td-1.1.dist-info/LICENSE
tariff_td-1.1.dist-info/METADATA
tariff_td-1.1.dist-info/WHEEL
tariff_td-1.1.dist-info/RECORD
