Metadata-Version: 2.1
Name: tariff-td
Version: 1.1
Summary: Calcula el periodo actual según las Tarifas Españolas TD 2.0 y 3.0
Home-page: https://github.com/miguelangellv/python-tariff-td
License: MIT
Author: Miguel Ángel López
Author-email: miguel.angel.lopez.vicente@gmail.com
Requires-Python: >=3.9
Classifier: License :: OSI Approved :: MIT License
Classifier: Programming Language :: Python :: 3
Classifier: Programming Language :: Python :: 3.9
Classifier: Programming Language :: Python :: 3.10
Classifier: Programming Language :: Python :: 3.11
Classifier: Programming Language :: Python :: 3.12
Requires-Dist: aiohttp (>=3.7.4.post0)
Requires-Dist: async_timeout (>=3.0.1)
Requires-Dist: holidays (>0.18)
Project-URL: Repository, https://github.com/miguelangellv/python-tariff-td
